torchtext-0.17.1.dist-info/RECORD
torchtext-0.17.1.dist-info/LICENSE
torchtext-0.17.1.dist-info/WHEEL
torchtext-0.17.1.dist-info/top_level.txt
torchtext-0.17.1.dist-info/METADATA
torchtext/transforms.py
torchtext/version.py
torchtext/_download_hooks.py
torchtext/__init__.py
torchtext/functional.py
torchtext/utils.py
torchtext/_torchtext.so
torchtext/_extension.py
torchtext/_internal/__init__.py
torchtext/_internal/module_utils.py
torchtext/experimental/vectors.py
torchtext/experimental/transforms.py
torchtext/experimental/__init__.py
torchtext/experimental/vocab_factory.py
torchtext/nn/__init__.py
torchtext/nn/modules/__init__.py
torchtext/nn/modules/multiheadattention.py
torchtext/datasets/yelpreviewfull.py
torchtext/datasets/dbpedia.py
torchtext/datasets/qqp.py
torchtext/datasets/udpos.py
torchtext/datasets/squad1.py
torchtext/datasets/enwik9.py
torchtext/datasets/sogounews.py
torchtext/datasets/__init__.py
torchtext/datasets/rte.py
torchtext/datasets/wikitext103.py
torchtext/datasets/sst2.py
torchtext/datasets/imdb.py
torchtext/datasets/qnli.py
torchtext/datasets/yelpreviewpolarity.py
torchtext/datasets/conll2000chunking.py
torchtext/datasets/cnndm.py
torchtext/datasets/wnli.py
torchtext/datasets/yahooanswers.py
torchtext/datasets/penntreebank.py
torchtext/datasets/cola.py
torchtext/datasets/amazonreviewpolarity.py
torchtext/datasets/iwslt2016.py
torchtext/datasets/squad2.py
torchtext/datasets/ag_news.py
torchtext/datasets/stsb.py
torchtext/datasets/mrpc.py
torchtext/datasets/amazonreviewfull.py
torchtext/datasets/wikitext2.py
torchtext/datasets/iwslt2017.py
torchtext/datasets/multi30k.py
torchtext/datasets/mnli.py
torchtext/datasets/cc100.py
torchtext/models/__init__.py
torchtext/models/t5/bundler.py
torchtext/models/t5/__init__.py
torchtext/models/t5/model.py
torchtext/models/t5/modules.py
torchtext/models/t5/t5_transform.py
torchtext/models/roberta/bundler.py
torchtext/models/roberta/__init__.py
torchtext/models/roberta/model.py
torchtext/models/roberta/modules.py
torchtext/prototype/vectors.py
torchtext/prototype/transforms.py
torchtext/prototype/generate.py
