Metadata-Version: 2.1
Name: torchtext
Version: 0.17.1
Summary: Text utilities, models, transforms, and datasets for PyTorch.
Home-page: https://github.com/pytorch/text
Author: PyTorch Text Team
Author-email: packages@pytorch.org
License: BSD
Classifier: Programming Language :: Python :: 3.8
Classifier: Programming Language :: Python :: 3.9
Classifier: Programming Language :: Python :: 3.10
Requires-Python: >=3.8
License-File: LICENSE
Requires-Dist: tqdm
Requires-Dist: requests
Requires-Dist: torch (==2.2.1)
Requires-Dist: numpy
Requires-Dist: torchdata (==0.7.1)
